[
    {
        "name": "southern_jungle",
        "location_size": 32,
        "location_border_thickness": 3,
        "img": "images/maps/southern_jungle.png"
    },
    {
        "name": "fe_village",
        "location_size": 24,
        "location_border_thickness": 2,
        "img": "images/maps/fe_village.png"
    },
    {
        "name": "quick_sand_fields",
        "location_size": 32,
        "location_border_thickness": 3,
        "img": "images/maps/quick_sand_fields.png"
    },
    {
        "name": "bugmuck",
        "location_size": 32,
        "location_border_thickness": 3,
        "img": "images/maps/bugmuck.png"
    },
    {
        "name": "northern_jungle",
        "location_size": 24,
        "location_border_thickness": 2,
        "img": "images/maps/northern_jungle.png"
    },
    {
        "name": "volcano_path",
        "location_size": 48,
        "location_border_thickness": 4,
        "img": "images/maps/volcano_path.png"
    },
    {
        "name": "swamp",
        "location_size": 48,
        "location_border_thickness": 4,
        "img": "images/maps/swamp.png"
    },
    {
        "name": "volcano_core",
        "location_size": 32,
        "location_border_thickness": 3,
        "img": "images/maps/volcano_core.png"
    },
    {
        "name": "volcano_sewers",
        "location_size": 48,
        "location_border_thickness": 4,
        "img": "images/maps/volcano_sewers.png"
    },
    {
        "name": "eastern_beach",
        "location_size": 24,
        "location_border_thickness": 2,
        "img": "images/maps/eastern_beach.png"
    },
    {
        "name": "crustacia",
        "location_size": 24,
        "location_border_thickness": 2,
        "img": "images/maps/crustacia.png"
    },
    {
        "name": "nobilia",
        "location_size": 48,
        "location_border_thickness": 4,
        "img": "images/maps/nobilia.png"
    },
    {
        "name": "river",
        "location_size": 24,
        "location_border_thickness": 2,
        "img": "images/maps/river.png"
    },
    {
        "name": "western_beach",
        "location_size": 32,
        "location_border_thickness": 3,
        "img": "images/maps/western_beach.png"
    },
    {
        "name": "pyramid_lower",
        "location_size": 32,
        "location_border_thickness": 3,
        "img": "images/maps/pyramid_lower.png"
    },
    {
        "name": "pyramid_upper",
        "location_size": 32,
        "location_border_thickness": 3,
        "img": "images/maps/pyramid_upper.png"
    },
    {
        "name": "halls_of_collosia_1",
        "location_size": 32,
        "location_border_thickness": 3,
        "img": "images/maps/halls_of_collosia_1.png"
    },
    {
        "name": "halls_of_collosia_2",
        "location_size": 48,
        "location_border_thickness": 4,
        "img": "images/maps/halls_of_collosia_2.png"
    },
    {
        "name": "halls_of_collosia_3",
        "location_size": 48,
        "location_border_thickness": 4,
        "img": "images/maps/halls_of_collosia_3.png"
    },
    {
        "name": "halls_of_collosia_4",
        "location_size": 48,
        "location_border_thickness": 4,
        "img": "images/maps/halls_of_collosia_4.png"
    },
    {
        "name": "tinys_hideout",
        "location_size": 32,
        "location_border_thickness": 3,
        "img": "images/maps/tinys_hideout.png"
    },
    {
        "name": "ebon_keep_interiors",
        "location_size": 48,
        "location_border_thickness": 4,
        "img": "images/maps/ebon_keep_interiors.png"
    },
    {
        "name": "ebon_keep",
        "location_size": 48,
        "location_border_thickness": 4,
        "img": "images/maps/ebon_keep.png"
    },
    {
        "name": "ebon_keep_sewers",
        "location_size": 32,
        "location_border_thickness": 3,
        "img": "images/maps/ebon_keep_sewers.png"
    },
    {
        "name": "dark_forest_1",
        "location_size": 128,
        "location_border_thickness": 12,
        "img": "images/maps/dark_forest_1.png"
    },
    {
        "name": "dark_forest_2",
        "location_size": 64,
        "location_border_thickness": 6,
        "img": "images/maps/dark_forest_2.png"
    },
    {
        "name": "chessboard",
        "location_size": 32,
        "location_border_thickness": 3,
        "img": "images/maps/chessboard.png"
    },
    {
        "name": "ivor_tower_interiors",
        "location_size": 48,
        "location_border_thickness": 4,
        "img": "images/maps/ivor_tower_interiors.png"
    },
    {
        "name": "ivor_tower",
        "location_size": 48,
        "location_border_thickness": 4,
        "img": "images/maps/ivor_tower.png"
    },
    {
        "name": "ivor_tower_sewers",
        "location_size": 32,
        "location_border_thickness": 3,
        "img": "images/maps/ivor_tower_sewers.png"
    },
    {
        "name": "gomi_tower",
        "location_size": 48,
        "location_border_thickness": 4,
        "img": "images/maps/gomi_tower.png"
    }
]